cpfr_rattlesnake-1.0.10.dist-info/licenses/LICENSE
rattlesnake/__init__.py
cpfr_rattlesnake-1.0.10.dist-info/METADATA
cpfr_rattlesnake-1.0.10.dist-info/WHEEL
cpfr_rattlesnake-1.0.10.dist-info/entry_points.txt
cpfr_rattlesnake-1.0.10.dist-info/top_level.txt
cpfr_rattlesnake-1.0.10.dist-info/RECORD
