Metadata-Version: 2.4
Name: cpfr-rattlesnake
Version: 1.0.10
Summary: A simple static-site generator for Python3, using markdown and the Jinja2 templating engine
Author-email: Carsten Pfeffer <pfeffer.carsten@gmail.com>
Keywords: static site generator,website,gitlab pages,jinja
Requires-Python: >=3.7
License-File: LICENSE
Requires-Dist: watchdog
Requires-Dist: jinja2
Requires-Dist: pyyaml
Requires-Dist: pyScss
Requires-Dist: termcolor
Requires-Dist: python-frontmatter
Requires-Dist: markdown
Requires-Dist: python-dateutil
Dynamic: license-file
